RealitySixAsync/__init__.py
RealitySixAsync/setup.py
Reality_six_async-0.0.0.dist-info/METADATA
Reality_six_async-0.0.0.dist-info/WHEEL
Reality_six_async-0.0.0.dist-info/top_level.txt
Reality_six_async-0.0.0.dist-info/RECORD
