Metadata-Version: 2.1
Name: Reality-six-async
Version: 0.0.0
Summary: A simple package that tells you reality. Async. Unsupported
Home-page: https://github.com/Hillo232/Reality/tree/async
Author: pkg_uploaders
Author-email: example@example.com
License: UNKNOWN
Platform: UNKNOWN
Classifier: Programming Language :: Python :: 3
Classifier: License :: OSI Approved :: MIT License
Classifier: Operating System :: OS Independent
Requires-Dist: psutil (>=5.8.0)
